qshap/__init__.py
qshap/main.py
qshap/qshap.py
qshap/tempCodeRunnerFile.py
qshap/test.py
qshap/utils.py
qshap/vis_module.py
qshap-0.3.6.dist-info/LICENSE
qshap-0.3.6.dist-info/METADATA
qshap-0.3.6.dist-info/WHEEL
qshap-0.3.6.dist-info/top_level.txt
qshap-0.3.6.dist-info/RECORD
