Metadata-Version: 2.1
Name: qshap
Version: 0.3.6
Summary: Exact computation of Shapley R-squared for tree ensembles in polynomial time
Home-page: https://github.com/catstats/Q-SHAP
Author: Zhongli Jiang, Dabao Zhang
Author-email: jiang548@purdue.edu, zdb969@hs.uci.edu
License: GPL-2.0
Classifier: Operating System :: Microsoft :: Windows
Classifier: Operating System :: Unix
Classifier: Operating System :: MacOS
Classifier: Programming Language :: Python :: 3.9
Classifier: Programming Language :: Python :: 3.10
Classifier: Programming Language :: Python :: 3.11
Classifier: Programming Language :: Python :: 3.12
Requires-Python: >=3.7
License-File: LICENSE
Requires-Dist: numpy
Requires-Dist: scikit-learn
Requires-Dist: shap
Requires-Dist: numba
Requires-Dist: ipywidgets
Requires-Dist: pandas
Requires-Dist: matplotlib
Provides-Extra: lightgbm
Requires-Dist: lightgbm ; extra == 'lightgbm'
Provides-Extra: xgboost
Requires-Dist: xgboost ; extra == 'xgboost'
